wcap/__init__.py
wcap/api.py
wcap/cli.py
wcap-0.3.0.dist-info/METADATA
wcap-0.3.0.dist-info/WHEEL
wcap-0.3.0.dist-info/entry_points.txt
wcap-0.3.0.dist-info/licenses/LICENSE
wcap-0.3.0.dist-info/RECORD
