Metadata-Version: 2.4
Name: wcap
Version: 0.3.0
Summary: Capture web pages as images using Selenium and the Firefox webdriver.
Project-URL: Documentation, https://github.com/yaph/wcap#readme
Project-URL: Issues, https://github.com/yaph/wcap/issues
Project-URL: Source, https://github.com/yaph/wcap
Author-email: Ramiro Gómez <code@ramiro.org>
License-Expression: MIT
License-File: LICENSE
Keywords: firefox,html to image,screenshot,selenium,webpage to image
Classifier: Development Status :: 4 - Beta
Classifier: Programming Language :: Python
Classifier: Programming Language :: Python :: 3.10
Classifier: Programming Language :: Python :: 3.11
Classifier: Programming Language :: Python :: 3.12
Classifier: Programming Language :: Python :: Implementation :: CPython
Classifier: Programming Language :: Python :: Implementation :: PyPy
Requires-Python: >=3.10
Requires-Dist: selenium
